cloud_weather_app/__init__.py
cloud_weather_app/weatherapp.py
cloud_weather_app-0.0.1.dist-info/LICENSE
cloud_weather_app-0.0.1.dist-info/METADATA
cloud_weather_app-0.0.1.dist-info/WHEEL
cloud_weather_app-0.0.1.dist-info/top_level.txt
cloud_weather_app-0.0.1.dist-info/RECORD
