Metadata-Version: 2.1
Name: cloud-weather-app
Version: 0.0.1
Summary: Simple Package to connect with weather.com endpoints and get quick info
Home-page: https://gitlab.com/0xdebug/cloud-weather
Author: Deepak Natanmai
License: UNKNOWN
Keywords: Weather api crawling scraping
Platform: UNKNOWN
Classifier: Programming Language :: Python :: 3
Classifier: Programming Language :: Python :: 2.7
Classifier: Programming Language :: Python :: 3.4
Classifier: Programming Language :: Python :: 3.5
Classifier: Programming Language :: Python :: 3.6
Classifier: Operating System :: OS Independent
Requires-Python: >=3.6
Requires-Dist: requests
Requires-Dist: beautifulsoup4
